{"lines": [{"xRight": 78, "yTop": 450, "yBottom": 488, "xLeft": 0}, {"xRight": 78, "yTop": 528, "yBottom": 556, "xLeft": 0}, {"xRight": 78, "yTop": 587, "yBottom": 618, "xLeft": 0}, {"xRight": 78, "yTop": 653, "yBottom": 698, "xLeft": 0}, {"xRight": 78, "yTop": 725, "yBottom": 756, "xLeft": 0}, {"xRight": 78, "yTop": 795, "yBottom": 826, "xLeft": 1}, {"xRight": 78, "yTop": 865, "yBottom": 895, "xLeft": 0}, {"xRight": 78, "yTop": 934, "yBottom": 964, "xLeft": 0}, {"xRight": 71, "yTop": 1004, "yBottom": 1034, "xLeft": 0}, {"xRight": 75, "yTop": 1071, "yBottom": 1103, "xLeft": 0}, {"xRight": 75, "yTop": 1151, "yBottom": 1180, "xLeft": 0}, {"xRight": 69, "yTop": 1210, "yBottom": 1241, "xLeft": 3}, {"xRight": 78, "yTop": 1290, "yBottom": 1319, "xLeft": 0}, {"xRight": 78, "yTop": 1348, "yBottom": 1379, "xLeft": 0}, {"xRight": 78, "yTop": 1465, "yBottom": 1494, "xLeft": 0}, {"xRight": 78, "yTop": 1525, "yBottom": 1563, "xLeft": 9}, {"xRight": 78, "yTop": 1604, "yBottom": 1632, "xLeft": 0}, {"xRight": 78, "yTop": 1700, "yBottom": 1731, "xLeft": 0}, {"xRight": 78, "yTop": 1770, "yBottom": 1801, "xLeft": 3}, {"xRight": 69, "yTop": 1839, "yBottom": 1870, "xLeft": 0}, {"xRight": 78, "yTop": 1909, "yBottom": 1940, "xLeft": 0}, {"xRight": 78, "yTop": 1979, "yBottom": 2008, "xLeft": 0}, {"xRight": 78, "yTop": 2051, "yBottom": 2078, "xLeft": 1}, {"xRight": 78, "yTop": 2175, "yBottom": 2205, "xLeft": 4}, {"xRight": 71, "yTop": 2281, "yBottom": 2302, "xLeft": 0}, {"xRight": 78, "yTop": 2342, "yBottom": 2372, "xLeft": 2}, {"xRight": 78, "yTop": 2590, "yBottom": 2621, "xLeft": 0}, {"xRight": 78, "yTop": 2660, "yBottom": 2691, "xLeft": 0}, {"xRight": 78, "yTop": 2731, "yBottom": 2760, "xLeft": 3}, {"xRight": 78, "yTop": 2798, "yBottom": 2829, "xLeft": 0}, {"xRight": 78, "yTop": 2866, "yBottom": 2898, "xLeft": 0}]}