{"lines": [{"xRight": 38, "yTop": 141, "yBottom": 154, "xLeft": 0}, {"xRight": 29, "yTop": 182, "yBottom": 202, "xLeft": 0}, {"xRight": 38, "yTop": 237, "yBottom": 256, "xLeft": 0}, {"xRight": 38, "yTop": 285, "yBottom": 298, "xLeft": 0}, {"xRight": 38, "yTop": 333, "yBottom": 347, "xLeft": 0}, {"xRight": 38, "yTop": 375, "yBottom": 395, "xLeft": 0}, {"xRight": 38, "yTop": 429, "yBottom": 448, "xLeft": 0}, {"xRight": 38, "yTop": 471, "yBottom": 491, "xLeft": 3}, {"xRight": 38, "yTop": 526, "yBottom": 539, "xLeft": 0}, {"xRight": 38, "yTop": 568, "yBottom": 587, "xLeft": 0}, {"xRight": 38, "yTop": 622, "yBottom": 636, "xLeft": 3}, {"xRight": 38, "yTop": 664, "yBottom": 690, "xLeft": 0}, {"xRight": 38, "yTop": 712, "yBottom": 732, "xLeft": 0}, {"xRight": 38, "yTop": 761, "yBottom": 780, "xLeft": 2}, {"xRight": 38, "yTop": 809, "yBottom": 829, "xLeft": 0}, {"xRight": 38, "yTop": 858, "yBottom": 878, "xLeft": 0}, {"xRight": 38, "yTop": 907, "yBottom": 931, "xLeft": 0}, {"xRight": 38, "yTop": 961, "yBottom": 975, "xLeft": 1}, {"xRight": 35, "yTop": 1003, "yBottom": 1023, "xLeft": 10}, {"xRight": 38, "yTop": 1051, "yBottom": 1071, "xLeft": 0}, {"xRight": 38, "yTop": 1105, "yBottom": 1119, "xLeft": 5}, {"xRight": 38, "yTop": 1153, "yBottom": 1167, "xLeft": 17}, {"xRight": 38, "yTop": 1195, "yBottom": 1215, "xLeft": 1}, {"xRight": 38, "yTop": 1346, "yBottom": 1348, "xLeft": 0}, {"xRight": 38, "yTop": 1367, "yBottom": 1386, "xLeft": 9}, {"xRight": 38, "yTop": 1394, "yBottom": 1411, "xLeft": 0}, {"xRight": 36, "yTop": 1438, "yBottom": 1456, "xLeft": 0}]}