{"lines": [{"xRight": 52, "yTop": 334, "yBottom": 351, "xLeft": 0}, {"xRight": 33, "yTop": 367, "yBottom": 384, "xLeft": 0}, {"xRight": 52, "yTop": 401, "yBottom": 418, "xLeft": 17}, {"xRight": 32, "yTop": 430, "yBottom": 451, "xLeft": 0}, {"xRight": 52, "yTop": 463, "yBottom": 485, "xLeft": 0}, {"xRight": 52, "yTop": 498, "yBottom": 519, "xLeft": 17}, {"xRight": 50, "yTop": 531, "yBottom": 558, "xLeft": 0}, {"xRight": 52, "yTop": 604, "yBottom": 620, "xLeft": 0}, {"xRight": 29, "yTop": 638, "yBottom": 654, "xLeft": 0}, {"xRight": 51, "yTop": 665, "yBottom": 687, "xLeft": 0}, {"xRight": 52, "yTop": 699, "yBottom": 721, "xLeft": 0}, {"xRight": 52, "yTop": 764, "yBottom": 788, "xLeft": 0}, {"xRight": 52, "yTop": 797, "yBottom": 820, "xLeft": 16}, {"xRight": 51, "yTop": 832, "yBottom": 853, "xLeft": 0}, {"xRight": 52, "yTop": 871, "yBottom": 891, "xLeft": 0}, {"xRight": 52, "yTop": 904, "yBottom": 922, "xLeft": 0}, {"xRight": 51, "yTop": 939, "yBottom": 955, "xLeft": 0}, {"xRight": 52, "yTop": 966, "yBottom": 988, "xLeft": 0}, {"xRight": 51, "yTop": 1000, "yBottom": 1022, "xLeft": 0}, {"xRight": 51, "yTop": 1100, "yBottom": 1122, "xLeft": 15}, {"xRight": 49, "yTop": 1134, "yBottom": 1156, "xLeft": 16}, {"xRight": 50, "yTop": 1168, "yBottom": 1190, "xLeft": 0}, {"xRight": 48, "yTop": 1202, "yBottom": 1224, "xLeft": 0}, {"xRight": 49, "yTop": 1236, "yBottom": 1258, "xLeft": 15}, {"xRight": 28, "yTop": 1337, "yBottom": 1359, "xLeft": 0}, {"xRight": 29, "yTop": 1371, "yBottom": 1393, "xLeft": 0}, {"xRight": 49, "yTop": 1405, "yBottom": 1433, "xLeft": 0}, {"xRight": 50, "yTop": 1433, "yBottom": 1461, "xLeft": 0}, {"xRight": 49, "yTop": 1479, "yBottom": 1495, "xLeft": 11}, {"xRight": 51, "yTop": 1507, "yBottom": 1529, "xLeft": 0}, {"xRight": 30, "yTop": 1547, "yBottom": 1564, "xLeft": 0}, {"xRight": 48, "yTop": 1581, "yBottom": 1597, "xLeft": 0}, {"xRight": 28, "yTop": 1681, "yBottom": 1699, "xLeft": 0}, {"xRight": 49, "yTop": 1716, "yBottom": 1737, "xLeft": 0}, {"xRight": 49, "yTop": 1816, "yBottom": 1836, "xLeft": 0}, {"xRight": 48, "yTop": 1844, "yBottom": 1866, "xLeft": 0}, {"xRight": 30, "yTop": 1878, "yBottom": 1901, "xLeft": 0}, {"xRight": 52, "yTop": 1912, "yBottom": 1933, "xLeft": 0}, {"xRight": 50, "yTop": 1951, "yBottom": 1971, "xLeft": 0}, {"xRight": 3, "yTop": 1971, "yBottom": 1973, "xLeft": 0}]}