{"lines": [{"xRight": 38, "yTop": 282, "yBottom": 296, "xLeft": 0}, {"xRight": 38, "yTop": 323, "yBottom": 343, "xLeft": 0}, {"xRight": 38, "yTop": 377, "yBottom": 391, "xLeft": 0}, {"xRight": 36, "yTop": 418, "yBottom": 439, "xLeft": 0}, {"xRight": 38, "yTop": 467, "yBottom": 491, "xLeft": 0}, {"xRight": 36, "yTop": 514, "yBottom": 534, "xLeft": 1}, {"xRight": 38, "yTop": 568, "yBottom": 588, "xLeft": 0}, {"xRight": 38, "yTop": 609, "yBottom": 629, "xLeft": 0}, {"xRight": 38, "yTop": 657, "yBottom": 676, "xLeft": 16}, {"xRight": 38, "yTop": 705, "yBottom": 723, "xLeft": 25}, {"xRight": 37, "yTop": 751, "yBottom": 771, "xLeft": 10}, {"xRight": 38, "yTop": 852, "yBottom": 865, "xLeft": 0}, {"xRight": 38, "yTop": 900, "yBottom": 913, "xLeft": 0}, {"xRight": 38, "yTop": 947, "yBottom": 961, "xLeft": 0}, {"xRight": 25, "yTop": 989, "yBottom": 1009, "xLeft": 0}, {"xRight": 38, "yTop": 1037, "yBottom": 1057, "xLeft": 0}, {"xRight": 38, "yTop": 1085, "yBottom": 1105, "xLeft": 0}, {"xRight": 38, "yTop": 1132, "yBottom": 1152, "xLeft": 0}, {"xRight": 32, "yTop": 1180, "yBottom": 1199, "xLeft": 0}, {"xRight": 38, "yTop": 1233, "yBottom": 1246, "xLeft": 6}, {"xRight": 38, "yTop": 1273, "yBottom": 1293, "xLeft": 0}, {"xRight": 38, "yTop": 1385, "yBottom": 1404, "xLeft": 0}]}