{"lines": [{"xRight": 53, "yTop": 242, "yBottom": 259, "xLeft": 0}, {"xRight": 53, "yTop": 338, "yBottom": 361, "xLeft": 25}, {"xRight": 53, "yTop": 372, "yBottom": 394, "xLeft": 4}, {"xRight": 53, "yTop": 412, "yBottom": 429, "xLeft": 0}, {"xRight": 53, "yTop": 473, "yBottom": 501, "xLeft": 0}, {"xRight": 53, "yTop": 507, "yBottom": 529, "xLeft": 5}, {"xRight": 53, "yTop": 542, "yBottom": 564, "xLeft": 0}, {"xRight": 53, "yTop": 574, "yBottom": 596, "xLeft": 24}, {"xRight": 53, "yTop": 607, "yBottom": 630, "xLeft": 5}, {"xRight": 53, "yTop": 640, "yBottom": 662, "xLeft": 26}, {"xRight": 53, "yTop": 675, "yBottom": 696, "xLeft": 0}, {"xRight": 42, "yTop": 713, "yBottom": 729, "xLeft": 0}, {"xRight": 53, "yTop": 741, "yBottom": 770, "xLeft": 4}, {"xRight": 42, "yTop": 775, "yBottom": 797, "xLeft": 4}, {"xRight": 42, "yTop": 814, "yBottom": 831, "xLeft": 0}, {"xRight": 53, "yTop": 848, "yBottom": 864, "xLeft": 25}, {"xRight": 43, "yTop": 881, "yBottom": 898, "xLeft": 0}, {"xRight": 53, "yTop": 980, "yBottom": 1003, "xLeft": 0}, {"xRight": 53, "yTop": 1014, "yBottom": 1031, "xLeft": 6}, {"xRight": 53, "yTop": 1042, "yBottom": 1064, "xLeft": 0}, {"xRight": 53, "yTop": 1076, "yBottom": 1098, "xLeft": 27}, {"xRight": 53, "yTop": 1110, "yBottom": 1132, "xLeft": 0}, {"xRight": 53, "yTop": 1182, "yBottom": 1206, "xLeft": 0}, {"xRight": 53, "yTop": 1210, "yBottom": 1238, "xLeft": 0}, {"xRight": 53, "yTop": 1250, "yBottom": 1266, "xLeft": 27}, {"xRight": 46, "yTop": 1280, "yBottom": 1301, "xLeft": 0}, {"xRight": 53, "yTop": 1345, "yBottom": 1372, "xLeft": 0}, {"xRight": 53, "yTop": 1384, "yBottom": 1400, "xLeft": 0}, {"xRight": 53, "yTop": 1412, "yBottom": 1434, "xLeft": 0}, {"xRight": 46, "yTop": 1452, "yBottom": 1469, "xLeft": 0}, {"xRight": 53, "yTop": 1480, "yBottom": 1502, "xLeft": 30}, {"xRight": 53, "yTop": 1587, "yBottom": 1609, "xLeft": 0}, {"xRight": 53, "yTop": 1615, "yBottom": 1637, "xLeft": 0}, {"xRight": 53, "yTop": 1649, "yBottom": 1671, "xLeft": 12}, {"xRight": 46, "yTop": 1685, "yBottom": 1705, "xLeft": 0}, {"xRight": 47, "yTop": 1717, "yBottom": 1739, "xLeft": 0}, {"xRight": 48, "yTop": 1756, "yBottom": 1772, "xLeft": 0}, {"xRight": 53, "yTop": 1783, "yBottom": 1806, "xLeft": 0}, {"xRight": 26, "yTop": 1823, "yBottom": 1846, "xLeft": 0}, {"xRight": 53, "yTop": 1857, "yBottom": 1872, "xLeft": 11}, {"xRight": 52, "yTop": 1923, "yBottom": 1946, "xLeft": 0}]}