{"lines": [{"xRight": 26, "yTop": 277, "yBottom": 296, "xLeft": 0}, {"xRight": 60, "yTop": 314, "yBottom": 342, "xLeft": 0}, {"xRight": 60, "yTop": 369, "yBottom": 389, "xLeft": 0}, {"xRight": 45, "yTop": 415, "yBottom": 435, "xLeft": 0}, {"xRight": 60, "yTop": 454, "yBottom": 481, "xLeft": 0}, {"xRight": 60, "yTop": 501, "yBottom": 527, "xLeft": 0}, {"xRight": 60, "yTop": 553, "yBottom": 572, "xLeft": 5}, {"xRight": 60, "yTop": 590, "yBottom": 618, "xLeft": 3}, {"xRight": 57, "yTop": 635, "yBottom": 663, "xLeft": 17}, {"xRight": 59, "yTop": 690, "yBottom": 710, "xLeft": 19}, {"xRight": 60, "yTop": 738, "yBottom": 757, "xLeft": 0}, {"xRight": 60, "yTop": 777, "yBottom": 804, "xLeft": 0}, {"xRight": 60, "yTop": 823, "yBottom": 851, "xLeft": 0}, {"xRight": 60, "yTop": 879, "yBottom": 898, "xLeft": 0}, {"xRight": 60, "yTop": 915, "yBottom": 944, "xLeft": 0}, {"xRight": 60, "yTop": 971, "yBottom": 990, "xLeft": 0}, {"xRight": 36, "yTop": 1017, "yBottom": 1037, "xLeft": 0}, {"xRight": 60, "yTop": 1054, "yBottom": 1083, "xLeft": 0}, {"xRight": 60, "yTop": 1194, "yBottom": 1221, "xLeft": 0}, {"xRight": 60, "yTop": 1288, "yBottom": 1315, "xLeft": 0}, {"xRight": 60, "yTop": 1334, "yBottom": 1369, "xLeft": 0}, {"xRight": 60, "yTop": 1389, "yBottom": 1408, "xLeft": 0}, {"xRight": 60, "yTop": 1426, "yBottom": 1455, "xLeft": 0}, {"xRight": 60, "yTop": 1474, "yBottom": 1501, "xLeft": 0}, {"xRight": 20, "yTop": 1518, "yBottom": 1554, "xLeft": 0}, {"xRight": 54, "yTop": 1566, "yBottom": 1600, "xLeft": 0}, {"xRight": 60, "yTop": 1622, "yBottom": 1647, "xLeft": 0}, {"xRight": 50, "yTop": 1659, "yBottom": 1688, "xLeft": 0}, {"xRight": 60, "yTop": 1715, "yBottom": 1734, "xLeft": 4}, {"xRight": 60, "yTop": 1752, "yBottom": 1779, "xLeft": 0}, {"xRight": 59, "yTop": 1799, "yBottom": 1833, "xLeft": 11}, {"xRight": 60, "yTop": 1853, "yBottom": 1872, "xLeft": 0}, {"xRight": 60, "yTop": 1899, "yBottom": 1919, "xLeft": 0}, {"xRight": 59, "yTop": 1937, "yBottom": 1965, "xLeft": 10}, {"xRight": 60, "yTop": 1985, "yBottom": 2012, "xLeft": 0}, {"xRight": 59, "yTop": 2039, "yBottom": 2065, "xLeft": 0}, {"xRight": 60, "yTop": 2076, "yBottom": 2105, "xLeft": 0}, {"xRight": 60, "yTop": 2132, "yBottom": 2151, "xLeft": 0}, {"xRight": 37, "yTop": 2178, "yBottom": 2198, "xLeft": 0}, {"xRight": 60, "yTop": 2218, "yBottom": 2244, "xLeft": 0}]}