{"lines": [{"xRight": 60, "yTop": 248, "yBottom": 267, "xLeft": 0}, {"xRight": 60, "yTop": 286, "yBottom": 313, "xLeft": 9}, {"xRight": 60, "yTop": 377, "yBottom": 405, "xLeft": 0}, {"xRight": 60, "yTop": 425, "yBottom": 451, "xLeft": 0}, {"xRight": 60, "yTop": 471, "yBottom": 502, "xLeft": 0}, {"xRight": 60, "yTop": 514, "yBottom": 542, "xLeft": 0}, {"xRight": 44, "yTop": 561, "yBottom": 588, "xLeft": 0}, {"xRight": 60, "yTop": 607, "yBottom": 634, "xLeft": 0}, {"xRight": 58, "yTop": 655, "yBottom": 681, "xLeft": 20}, {"xRight": 60, "yTop": 701, "yBottom": 729, "xLeft": 4}, {"xRight": 60, "yTop": 745, "yBottom": 774, "xLeft": 0}, {"xRight": 60, "yTop": 792, "yBottom": 820, "xLeft": 0}, {"xRight": 52, "yTop": 840, "yBottom": 867, "xLeft": 0}, {"xRight": 60, "yTop": 976, "yBottom": 1005, "xLeft": 1}, {"xRight": 60, "yTop": 1070, "yBottom": 1104, "xLeft": 0}, {"xRight": 56, "yTop": 1116, "yBottom": 1146, "xLeft": 16}, {"xRight": 60, "yTop": 1162, "yBottom": 1191, "xLeft": 0}, {"xRight": 60, "yTop": 1218, "yBottom": 1238, "xLeft": 0}, {"xRight": 60, "yTop": 1265, "yBottom": 1284, "xLeft": 0}, {"xRight": 60, "yTop": 1302, "yBottom": 1332, "xLeft": 0}, {"xRight": 58, "yTop": 1359, "yBottom": 1379, "xLeft": 0}, {"xRight": 37, "yTop": 1406, "yBottom": 1425, "xLeft": 0}, {"xRight": 60, "yTop": 1443, "yBottom": 1472, "xLeft": 0}, {"xRight": 60, "yTop": 1498, "yBottom": 1518, "xLeft": 12}, {"xRight": 58, "yTop": 1537, "yBottom": 1565, "xLeft": 0}, {"xRight": 60, "yTop": 1590, "yBottom": 1610, "xLeft": 17}, {"xRight": 56, "yTop": 1629, "yBottom": 1657, "xLeft": 0}, {"xRight": 34, "yTop": 1684, "yBottom": 1704, "xLeft": 0}, {"xRight": 60, "yTop": 1730, "yBottom": 1750, "xLeft": 0}, {"xRight": 40, "yTop": 1824, "yBottom": 1844, "xLeft": 0}, {"xRight": 60, "yTop": 1907, "yBottom": 1936, "xLeft": 11}, {"xRight": 58, "yTop": 1955, "yBottom": 1982, "xLeft": 0}, {"xRight": 60, "yTop": 2008, "yBottom": 2027, "xLeft": 24}, {"xRight": 60, "yTop": 2045, "yBottom": 2074, "xLeft": 0}, {"xRight": 43, "yTop": 2091, "yBottom": 2125, "xLeft": 0}, {"xRight": 60, "yTop": 2137, "yBottom": 2166, "xLeft": 0}, {"xRight": 60, "yTop": 2193, "yBottom": 2212, "xLeft": 0}, {"xRight": 60, "yTop": 2230, "yBottom": 2263, "xLeft": 0}, {"xRight": 60, "yTop": 2274, "yBottom": 2303, "xLeft": 0}]}