{"lines": [{"xRight": 53, "yTop": 209, "yBottom": 237, "xLeft": 0}, {"xRight": 56, "yTop": 338, "yBottom": 368, "xLeft": 0}, {"xRight": 56, "yTop": 373, "yBottom": 401, "xLeft": 0}, {"xRight": 56, "yTop": 427, "yBottom": 448, "xLeft": 0}, {"xRight": 53, "yTop": 462, "yBottom": 489, "xLeft": 0}, {"xRight": 56, "yTop": 513, "yBottom": 533, "xLeft": 0}, {"xRight": 27, "yTop": 558, "yBottom": 577, "xLeft": 0}, {"xRight": 36, "yTop": 595, "yBottom": 620, "xLeft": 0}, {"xRight": 56, "yTop": 724, "yBottom": 753, "xLeft": 0}, {"xRight": 56, "yTop": 769, "yBottom": 806, "xLeft": 0}, {"xRight": 56, "yTop": 815, "yBottom": 841, "xLeft": 0}, {"xRight": 52, "yTop": 857, "yBottom": 886, "xLeft": 6}, {"xRight": 56, "yTop": 943, "yBottom": 972, "xLeft": 0}, {"xRight": 54, "yTop": 989, "yBottom": 1015, "xLeft": 0}, {"xRight": 56, "yTop": 1028, "yBottom": 1057, "xLeft": 0}, {"xRight": 56, "yTop": 1078, "yBottom": 1098, "xLeft": 23}, {"xRight": 56, "yTop": 1114, "yBottom": 1142, "xLeft": 0}, {"xRight": 56, "yTop": 1165, "yBottom": 1185, "xLeft": 0}, {"xRight": 56, "yTop": 1200, "yBottom": 1239, "xLeft": 0}, {"xRight": 52, "yTop": 1244, "yBottom": 1272, "xLeft": 0}, {"xRight": 53, "yTop": 1290, "yBottom": 1316, "xLeft": 0}, {"xRight": 56, "yTop": 1338, "yBottom": 1358, "xLeft": 0}, {"xRight": 56, "yTop": 1468, "yBottom": 1496, "xLeft": 0}, {"xRight": 56, "yTop": 1509, "yBottom": 1532, "xLeft": 0}, {"xRight": 56, "yTop": 1555, "yBottom": 1583, "xLeft": 11}, {"xRight": 56, "yTop": 1598, "yBottom": 1618, "xLeft": 0}, {"xRight": 56, "yTop": 1632, "yBottom": 1661, "xLeft": 0}, {"xRight": 56, "yTop": 1676, "yBottom": 1705, "xLeft": 21}, {"xRight": 56, "yTop": 1764, "yBottom": 1793, "xLeft": 0}, {"xRight": 56, "yTop": 1816, "yBottom": 1836, "xLeft": 2}, {"xRight": 56, "yTop": 1851, "yBottom": 1879, "xLeft": 0}, {"xRight": 56, "yTop": 1903, "yBottom": 1923, "xLeft": 4}, {"xRight": 56, "yTop": 1938, "yBottom": 1967, "xLeft": 0}, {"xRight": 56, "yTop": 1982, "yBottom": 2018, "xLeft": 6}, {"xRight": 56, "yTop": 2036, "yBottom": 2056, "xLeft": 12}]}