{"lines": [{"xRight": 992, "yTop": 150, "yBottom": 187, "xLeft": 417}, {"xRight": 1254, "yTop": 232, "yBottom": 279, "xLeft": 158}, {"xRight": 1255, "yTop": 290, "yBottom": 344, "xLeft": 157}, {"xRight": 1255, "yTop": 347, "yBottom": 392, "xLeft": 158}, {"xRight": 1253, "yTop": 405, "yBottom": 459, "xLeft": 158}, {"xRight": 1252, "yTop": 463, "yBottom": 510, "xLeft": 156}, {"xRight": 1255, "yTop": 521, "yBottom": 576, "xLeft": 157}, {"xRight": 446, "yTop": 592, "yBottom": 625, "xLeft": 157}, {"xRight": 1255, "yTop": 637, "yBottom": 682, "xLeft": 203}, {"xRight": 1256, "yTop": 695, "yBottom": 750, "xLeft": 158}, {"xRight": 1256, "yTop": 755, "yBottom": 799, "xLeft": 158}, {"xRight": 1254, "yTop": 815, "yBottom": 862, "xLeft": 158}, {"xRight": 1254, "yTop": 871, "yBottom": 926, "xLeft": 157}, {"xRight": 1255, "yTop": 929, "yBottom": 973, "xLeft": 157}, {"xRight": 1254, "yTop": 988, "yBottom": 1039, "xLeft": 158}, {"xRight": 1253, "yTop": 1046, "yBottom": 1094, "xLeft": 157}, {"xRight": 1254, "yTop": 1105, "yBottom": 1158, "xLeft": 156}, {"xRight": 1254, "yTop": 1162, "yBottom": 1212, "xLeft": 156}, {"xRight": 1255, "yTop": 1219, "yBottom": 1274, "xLeft": 156}, {"xRight": 1254, "yTop": 1278, "yBottom": 1327, "xLeft": 156}, {"xRight": 1254, "yTop": 1338, "yBottom": 1378, "xLeft": 156}, {"xRight": 1255, "yTop": 1395, "yBottom": 1448, "xLeft": 155}, {"xRight": 1253, "yTop": 1454, "yBottom": 1503, "xLeft": 155}, {"xRight": 1253, "yTop": 1511, "yBottom": 1563, "xLeft": 153}, {"xRight": 1254, "yTop": 1570, "yBottom": 1618, "xLeft": 155}, {"xRight": 1252, "yTop": 1628, "yBottom": 1680, "xLeft": 154}, {"xRight": 1255, "yTop": 1687, "yBottom": 1735, "xLeft": 155}, {"xRight": 1254, "yTop": 1746, "yBottom": 1793, "xLeft": 155}, {"xRight": 1254, "yTop": 1808, "yBottom": 1860, "xLeft": 155}, {"xRight": 567, "yTop": 1867, "yBottom": 1913, "xLeft": 155}, {"xRight": 1255, "yTop": 1921, "yBottom": 1972, "xLeft": 201}, {"xRight": 724, "yTop": 1995, "yBottom": 2038, "xLeft": 682}]}