{"lines": [{"xRight": 54, "yTop": 213, "yBottom": 234, "xLeft": 0}, {"xRight": 54, "yTop": 251, "yBottom": 281, "xLeft": 0}, {"xRight": 53, "yTop": 298, "yBottom": 336, "xLeft": 0}, {"xRight": 54, "yTop": 344, "yBottom": 375, "xLeft": 16}, {"xRight": 54, "yTop": 391, "yBottom": 421, "xLeft": 0}, {"xRight": 54, "yTop": 446, "yBottom": 468, "xLeft": 1}, {"xRight": 54, "yTop": 484, "yBottom": 515, "xLeft": 0}, {"xRight": 54, "yTop": 586, "yBottom": 608, "xLeft": 0}, {"xRight": 54, "yTop": 625, "yBottom": 663, "xLeft": 0}, {"xRight": 54, "yTop": 680, "yBottom": 701, "xLeft": 22}, {"xRight": 53, "yTop": 718, "yBottom": 748, "xLeft": 3}, {"xRight": 54, "yTop": 773, "yBottom": 802, "xLeft": 0}, {"xRight": 54, "yTop": 820, "yBottom": 841, "xLeft": 13}, {"xRight": 52, "yTop": 866, "yBottom": 888, "xLeft": 0}, {"xRight": 54, "yTop": 913, "yBottom": 935, "xLeft": 0}, {"xRight": 54, "yTop": 1007, "yBottom": 1027, "xLeft": 0}, {"xRight": 54, "yTop": 1045, "yBottom": 1075, "xLeft": 0}, {"xRight": 54, "yTop": 1094, "yBottom": 1129, "xLeft": 0}, {"xRight": 54, "yTop": 1137, "yBottom": 1167, "xLeft": 0}, {"xRight": 54, "yTop": 1184, "yBottom": 1215, "xLeft": 16}, {"xRight": 52, "yTop": 1240, "yBottom": 1261, "xLeft": 0}, {"xRight": 54, "yTop": 1286, "yBottom": 1308, "xLeft": 21}, {"xRight": 54, "yTop": 1325, "yBottom": 1355, "xLeft": 11}, {"xRight": 54, "yTop": 1380, "yBottom": 1401, "xLeft": 13}, {"xRight": 53, "yTop": 1465, "yBottom": 1495, "xLeft": 3}, {"xRight": 54, "yTop": 1511, "yBottom": 1541, "xLeft": 0}, {"xRight": 53, "yTop": 1557, "yBottom": 1588, "xLeft": 18}, {"xRight": 54, "yTop": 1604, "yBottom": 1635, "xLeft": 6}, {"xRight": 54, "yTop": 1651, "yBottom": 1690, "xLeft": 0}, {"xRight": 54, "yTop": 1753, "yBottom": 1775, "xLeft": 0}, {"xRight": 54, "yTop": 1800, "yBottom": 1821, "xLeft": 0}, {"xRight": 54, "yTop": 1846, "yBottom": 1868, "xLeft": 0}, {"xRight": 54, "yTop": 1884, "yBottom": 1915, "xLeft": 0}, {"xRight": 54, "yTop": 1931, "yBottom": 1961, "xLeft": 0}, {"xRight": 54, "yTop": 1986, "yBottom": 2008, "xLeft": 0}, {"xRight": 54, "yTop": 2024, "yBottom": 2055, "xLeft": 0}, {"xRight": 54, "yTop": 2207, "yBottom": 2233, "xLeft": 17}]}