{"lines": [{"xRight": 23, "yTop": 127, "yBottom": 146, "xLeft": 4}, {"xRight": 38, "yTop": 174, "yBottom": 193, "xLeft": 4}, {"xRight": 34, "yTop": 221, "yBottom": 240, "xLeft": 0}, {"xRight": 33, "yTop": 271, "yBottom": 288, "xLeft": 1}, {"xRight": 38, "yTop": 315, "yBottom": 340, "xLeft": 0}, {"xRight": 38, "yTop": 362, "yBottom": 387, "xLeft": 0}, {"xRight": 38, "yTop": 416, "yBottom": 429, "xLeft": 0}, {"xRight": 38, "yTop": 457, "yBottom": 477, "xLeft": 0}, {"xRight": 24, "yTop": 507, "yBottom": 526, "xLeft": 4}, {"xRight": 38, "yTop": 554, "yBottom": 573, "xLeft": 5}, {"xRight": 37, "yTop": 607, "yBottom": 621, "xLeft": 12}, {"xRight": 37, "yTop": 656, "yBottom": 669, "xLeft": 0}, {"xRight": 38, "yTop": 703, "yBottom": 723, "xLeft": 0}, {"xRight": 38, "yTop": 748, "yBottom": 770, "xLeft": 0}, {"xRight": 38, "yTop": 806, "yBottom": 826, "xLeft": 5}, {"xRight": 38, "yTop": 853, "yBottom": 872, "xLeft": 6}, {"xRight": 38, "yTop": 906, "yBottom": 920, "xLeft": 8}, {"xRight": 29, "yTop": 954, "yBottom": 973, "xLeft": 0}, {"xRight": 38, "yTop": 1002, "yBottom": 1015, "xLeft": 0}, {"xRight": 25, "yTop": 1045, "yBottom": 1063, "xLeft": 8}, {"xRight": 38, "yTop": 1091, "yBottom": 1110, "xLeft": 6}, {"xRight": 33, "yTop": 1146, "yBottom": 1159, "xLeft": 0}, {"xRight": 38, "yTop": 1194, "yBottom": 1208, "xLeft": 0}, {"xRight": 37, "yTop": 1236, "yBottom": 1256, "xLeft": 0}, {"xRight": 36, "yTop": 1284, "yBottom": 1303, "xLeft": 7}, {"xRight": 38, "yTop": 1331, "yBottom": 1350, "xLeft": 4}, {"xRight": 38, "yTop": 1389, "yBottom": 1391, "xLeft": 0}, {"xRight": 38, "yTop": 1409, "yBottom": 1425, "xLeft": 0}]}