{"lines": [{"xRight": 21, "yTop": 110, "yBottom": 125, "xLeft": 1}, {"xRight": 21, "yTop": 134, "yBottom": 149, "xLeft": 1}, {"xRight": 21, "yTop": 158, "yBottom": 173, "xLeft": 1}, {"xRight": 21, "yTop": 182, "yBottom": 197, "xLeft": 0}, {"xRight": 13, "yTop": 207, "yBottom": 221, "xLeft": 0}, {"xRight": 21, "yTop": 231, "yBottom": 246, "xLeft": 0}, {"xRight": 21, "yTop": 256, "yBottom": 270, "xLeft": 1}, {"xRight": 21, "yTop": 279, "yBottom": 294, "xLeft": 2}, {"xRight": 21, "yTop": 308, "yBottom": 318, "xLeft": 0}, {"xRight": 21, "yTop": 327, "yBottom": 342, "xLeft": 0}, {"xRight": 18, "yTop": 352, "yBottom": 367, "xLeft": 0}, {"xRight": 21, "yTop": 376, "yBottom": 392, "xLeft": 0}, {"xRight": 21, "yTop": 400, "yBottom": 416, "xLeft": 4}, {"xRight": 21, "yTop": 425, "yBottom": 440, "xLeft": 5}, {"xRight": 21, "yTop": 450, "yBottom": 464, "xLeft": 0}, {"xRight": 21, "yTop": 478, "yBottom": 488, "xLeft": 13}, {"xRight": 21, "yTop": 500, "yBottom": 513, "xLeft": 0}, {"xRight": 21, "yTop": 522, "yBottom": 538, "xLeft": 0}, {"xRight": 21, "yTop": 551, "yBottom": 561, "xLeft": 0}, {"xRight": 20, "yTop": 571, "yBottom": 586, "xLeft": 10}, {"xRight": 21, "yTop": 600, "yBottom": 610, "xLeft": 0}, {"xRight": 21, "yTop": 620, "yBottom": 634, "xLeft": 8}, {"xRight": 21, "yTop": 649, "yBottom": 659, "xLeft": 11}, {"xRight": 20, "yTop": 673, "yBottom": 683, "xLeft": 11}, {"xRight": 21, "yTop": 692, "yBottom": 707, "xLeft": 0}, {"xRight": 21, "yTop": 717, "yBottom": 732, "xLeft": 0}, {"xRight": 21, "yTop": 741, "yBottom": 756, "xLeft": 13}, {"xRight": 21, "yTop": 765, "yBottom": 781, "xLeft": 1}, {"xRight": 21, "yTop": 790, "yBottom": 805, "xLeft": 0}, {"xRight": 21, "yTop": 818, "yBottom": 829, "xLeft": 0}, {"xRight": 21, "yTop": 841, "yBottom": 857, "xLeft": 0}, {"xRight": 21, "yTop": 865, "yBottom": 878, "xLeft": 0}]}