{"lines": [{"xRight": 56, "yTop": 211, "yBottom": 251, "xLeft": 0}, {"xRight": 56, "yTop": 262, "yBottom": 311, "xLeft": 5}, {"xRight": 56, "yTop": 311, "yBottom": 350, "xLeft": 0}, {"xRight": 56, "yTop": 363, "yBottom": 410, "xLeft": 0}, {"xRight": 56, "yTop": 410, "yBottom": 450, "xLeft": 1}, {"xRight": 56, "yTop": 461, "yBottom": 512, "xLeft": 0}, {"xRight": 56, "yTop": 512, "yBottom": 549, "xLeft": 0}, {"xRight": 56, "yTop": 562, "yBottom": 599, "xLeft": 0}, {"xRight": 56, "yTop": 611, "yBottom": 661, "xLeft": 0}, {"xRight": 56, "yTop": 661, "yBottom": 697, "xLeft": 0}, {"xRight": 56, "yTop": 710, "yBottom": 748, "xLeft": 0}, {"xRight": 56, "yTop": 761, "yBottom": 810, "xLeft": 0}, {"xRight": 56, "yTop": 813, "yBottom": 859, "xLeft": 0}, {"xRight": 35, "yTop": 860, "yBottom": 898, "xLeft": 0}, {"xRight": 56, "yTop": 909, "yBottom": 947, "xLeft": 0}, {"xRight": 56, "yTop": 960, "yBottom": 998, "xLeft": 0}, {"xRight": 56, "yTop": 1009, "yBottom": 1058, "xLeft": 0}, {"xRight": 56, "yTop": 1063, "yBottom": 1097, "xLeft": 0}, {"xRight": 56, "yTop": 1124, "yBottom": 1159, "xLeft": 0}, {"xRight": 56, "yTop": 1174, "yBottom": 1204, "xLeft": 48}, {"xRight": 56, "yTop": 1267, "yBottom": 1295, "xLeft": 51}, {"xRight": 49, "yTop": 1380, "yBottom": 1420, "xLeft": 0}, {"xRight": 44, "yTop": 1420, "yBottom": 1457, "xLeft": 0}, {"xRight": 56, "yTop": 1483, "yBottom": 1518, "xLeft": 10}, {"xRight": 56, "yTop": 1523, "yBottom": 1570, "xLeft": 12}, {"xRight": 56, "yTop": 1570, "yBottom": 1606, "xLeft": 0}, {"xRight": 56, "yTop": 1621, "yBottom": 1656, "xLeft": 0}, {"xRight": 56, "yTop": 1681, "yBottom": 1705, "xLeft": 18}, {"xRight": 56, "yTop": 1732, "yBottom": 1768, "xLeft": 0}, {"xRight": 56, "yTop": 1768, "yBottom": 1804, "xLeft": 0}, {"xRight": 56, "yTop": 1877, "yBottom": 1908, "xLeft": 0}, {"xRight": 56, "yTop": 1921, "yBottom": 1951, "xLeft": 19}, {"xRight": 56, "yTop": 1969, "yBottom": 1998, "xLeft": 0}, {"xRight": 56, "yTop": 2009, "yBottom": 2044, "xLeft": 19}]}