{"lines": [{"xRight": 38, "yTop": 148, "yBottom": 168, "xLeft": 0}, {"xRight": 38, "yTop": 193, "yBottom": 213, "xLeft": 0}, {"xRight": 38, "yTop": 243, "yBottom": 257, "xLeft": 0}, {"xRight": 38, "yTop": 287, "yBottom": 300, "xLeft": 0}, {"xRight": 38, "yTop": 329, "yBottom": 345, "xLeft": 0}, {"xRight": 38, "yTop": 371, "yBottom": 390, "xLeft": 0}, {"xRight": 38, "yTop": 420, "yBottom": 434, "xLeft": 2}, {"xRight": 38, "yTop": 465, "yBottom": 478, "xLeft": 0}, {"xRight": 38, "yTop": 517, "yBottom": 536, "xLeft": 0}, {"xRight": 38, "yTop": 565, "yBottom": 590, "xLeft": 5}, {"xRight": 33, "yTop": 613, "yBottom": 633, "xLeft": 0}, {"xRight": 38, "yTop": 724, "yBottom": 744, "xLeft": 0}, {"xRight": 38, "yTop": 778, "yBottom": 792, "xLeft": 0}, {"xRight": 34, "yTop": 820, "yBottom": 840, "xLeft": 0}, {"xRight": 38, "yTop": 919, "yBottom": 938, "xLeft": 0}, {"xRight": 38, "yTop": 972, "yBottom": 991, "xLeft": 0}, {"xRight": 38, "yTop": 1019, "yBottom": 1039, "xLeft": 0}, {"xRight": 38, "yTop": 1067, "yBottom": 1084, "xLeft": 0}, {"xRight": 36, "yTop": 1109, "yBottom": 1130, "xLeft": 0}, {"xRight": 38, "yTop": 1158, "yBottom": 1184, "xLeft": 0}, {"xRight": 38, "yTop": 1214, "yBottom": 1233, "xLeft": 0}, {"xRight": 37, "yTop": 1257, "yBottom": 1283, "xLeft": 0}, {"xRight": 32, "yTop": 1306, "yBottom": 1326, "xLeft": 0}, {"xRight": 38, "yTop": 1355, "yBottom": 1374, "xLeft": 0}]}