{"lines": [{"xRight": 38, "yTop": 148, "yBottom": 168, "xLeft": 0}, {"xRight": 38, "yTop": 193, "yBottom": 212, "xLeft": 0}, {"xRight": 38, "yTop": 238, "yBottom": 257, "xLeft": 0}, {"xRight": 38, "yTop": 285, "yBottom": 307, "xLeft": 0}, {"xRight": 38, "yTop": 326, "yBottom": 346, "xLeft": 0}, {"xRight": 38, "yTop": 370, "yBottom": 390, "xLeft": 0}, {"xRight": 38, "yTop": 415, "yBottom": 434, "xLeft": 0}, {"xRight": 37, "yTop": 459, "yBottom": 484, "xLeft": 0}, {"xRight": 37, "yTop": 522, "yBottom": 536, "xLeft": 0}, {"xRight": 37, "yTop": 571, "yBottom": 590, "xLeft": 0}, {"xRight": 38, "yTop": 613, "yBottom": 633, "xLeft": 0}, {"xRight": 38, "yTop": 668, "yBottom": 682, "xLeft": 0}, {"xRight": 38, "yTop": 724, "yBottom": 744, "xLeft": 0}, {"xRight": 38, "yTop": 778, "yBottom": 792, "xLeft": 1}, {"xRight": 38, "yTop": 820, "yBottom": 841, "xLeft": 0}, {"xRight": 38, "yTop": 869, "yBottom": 890, "xLeft": 0}, {"xRight": 36, "yTop": 919, "yBottom": 938, "xLeft": 6}, {"xRight": 32, "yTop": 967, "yBottom": 990, "xLeft": 0}, {"xRight": 38, "yTop": 1014, "yBottom": 1033, "xLeft": 0}, {"xRight": 38, "yTop": 1068, "yBottom": 1081, "xLeft": 0}, {"xRight": 38, "yTop": 1108, "yBottom": 1135, "xLeft": 0}, {"xRight": 38, "yTop": 1159, "yBottom": 1183, "xLeft": 7}, {"xRight": 37, "yTop": 1211, "yBottom": 1234, "xLeft": 0}, {"xRight": 38, "yTop": 1256, "yBottom": 1277, "xLeft": 0}, {"xRight": 29, "yTop": 1306, "yBottom": 1326, "xLeft": 0}, {"xRight": 38, "yTop": 1354, "yBottom": 1374, "xLeft": 0}]}