{"lines": [{"xRight": 52, "yTop": 315, "yBottom": 337, "xLeft": 19}, {"xRight": 52, "yTop": 351, "yBottom": 373, "xLeft": 2}, {"xRight": 52, "yTop": 397, "yBottom": 419, "xLeft": 3}, {"xRight": 52, "yTop": 436, "yBottom": 463, "xLeft": 2}, {"xRight": 52, "yTop": 469, "yBottom": 492, "xLeft": 3}, {"xRight": 52, "yTop": 509, "yBottom": 526, "xLeft": 2}, {"xRight": 52, "yTop": 609, "yBottom": 626, "xLeft": 3}, {"xRight": 52, "yTop": 637, "yBottom": 664, "xLeft": 1}, {"xRight": 52, "yTop": 672, "yBottom": 693, "xLeft": 41}, {"xRight": 52, "yTop": 711, "yBottom": 727, "xLeft": 4}, {"xRight": 37, "yTop": 744, "yBottom": 760, "xLeft": 4}, {"xRight": 52, "yTop": 772, "yBottom": 794, "xLeft": 3}, {"xRight": 52, "yTop": 811, "yBottom": 828, "xLeft": 4}, {"xRight": 52, "yTop": 838, "yBottom": 861, "xLeft": 2}, {"xRight": 52, "yTop": 872, "yBottom": 898, "xLeft": 21}, {"xRight": 52, "yTop": 911, "yBottom": 927, "xLeft": 1}, {"xRight": 52, "yTop": 939, "yBottom": 961, "xLeft": 5}, {"xRight": 52, "yTop": 1039, "yBottom": 1060, "xLeft": 3}, {"xRight": 52, "yTop": 1072, "yBottom": 1100, "xLeft": 0}, {"xRight": 52, "yTop": 1106, "yBottom": 1128, "xLeft": 0}, {"xRight": 52, "yTop": 1140, "yBottom": 1162, "xLeft": 5}, {"xRight": 52, "yTop": 1214, "yBottom": 1230, "xLeft": 23}, {"xRight": 52, "yTop": 1242, "yBottom": 1264, "xLeft": 4}, {"xRight": 52, "yTop": 1282, "yBottom": 1297, "xLeft": 6}, {"xRight": 52, "yTop": 1383, "yBottom": 1400, "xLeft": 25}, {"xRight": 40, "yTop": 1412, "yBottom": 1433, "xLeft": 4}, {"xRight": 52, "yTop": 1451, "yBottom": 1469, "xLeft": 0}, {"xRight": 52, "yTop": 1511, "yBottom": 1533, "xLeft": 25}, {"xRight": 52, "yTop": 1551, "yBottom": 1573, "xLeft": 23}, {"xRight": 52, "yTop": 1585, "yBottom": 1607, "xLeft": 0}, {"xRight": 52, "yTop": 1618, "yBottom": 1634, "xLeft": 0}, {"xRight": 52, "yTop": 1646, "yBottom": 1668, "xLeft": 0}, {"xRight": 52, "yTop": 1680, "yBottom": 1702, "xLeft": 23}, {"xRight": 52, "yTop": 1719, "yBottom": 1736, "xLeft": 22}, {"xRight": 52, "yTop": 1747, "yBottom": 1768, "xLeft": 26}, {"xRight": 52, "yTop": 1787, "yBottom": 1803, "xLeft": 7}, {"xRight": 52, "yTop": 1820, "yBottom": 1842, "xLeft": 8}, {"xRight": 52, "yTop": 1882, "yBottom": 1903, "xLeft": 0}, {"xRight": 52, "yTop": 1915, "yBottom": 1937, "xLeft": 0}]}