{"lines": [{"xRight": 77, "yTop": 399, "yBottom": 430, "xLeft": 0}, {"xRight": 77, "yTop": 468, "yBottom": 498, "xLeft": 0}, {"xRight": 77, "yTop": 536, "yBottom": 566, "xLeft": 0}, {"xRight": 77, "yTop": 604, "yBottom": 635, "xLeft": 9}, {"xRight": 77, "yTop": 673, "yBottom": 712, "xLeft": 0}, {"xRight": 77, "yTop": 741, "yBottom": 772, "xLeft": 0}, {"xRight": 77, "yTop": 811, "yBottom": 841, "xLeft": 0}, {"xRight": 77, "yTop": 889, "yBottom": 909, "xLeft": 13}, {"xRight": 77, "yTop": 946, "yBottom": 978, "xLeft": 0}, {"xRight": 77, "yTop": 1084, "yBottom": 1115, "xLeft": 0}, {"xRight": 77, "yTop": 1154, "yBottom": 1184, "xLeft": 0}, {"xRight": 77, "yTop": 1222, "yBottom": 1253, "xLeft": 0}, {"xRight": 77, "yTop": 1290, "yBottom": 1322, "xLeft": 0}, {"xRight": 77, "yTop": 1361, "yBottom": 1390, "xLeft": 0}, {"xRight": 77, "yTop": 1432, "yBottom": 1459, "xLeft": 0}, {"xRight": 77, "yTop": 1497, "yBottom": 1536, "xLeft": 0}, {"xRight": 77, "yTop": 1567, "yBottom": 1597, "xLeft": 0}, {"xRight": 77, "yTop": 1634, "yBottom": 1666, "xLeft": 0}, {"xRight": 77, "yTop": 1704, "yBottom": 1734, "xLeft": 0}, {"xRight": 77, "yTop": 1842, "yBottom": 1871, "xLeft": 9}, {"xRight": 77, "yTop": 1919, "yBottom": 1939, "xLeft": 0}, {"xRight": 77, "yTop": 1978, "yBottom": 2016, "xLeft": 0}, {"xRight": 77, "yTop": 2046, "yBottom": 2077, "xLeft": 0}, {"xRight": 77, "yTop": 2192, "yBottom": 2214, "xLeft": 0}, {"xRight": 77, "yTop": 2251, "yBottom": 2282, "xLeft": 0}, {"xRight": 77, "yTop": 2322, "yBottom": 2350, "xLeft": 0}, {"xRight": 77, "yTop": 2398, "yBottom": 2427, "xLeft": 5}, {"xRight": 75, "yTop": 2472, "yBottom": 2502, "xLeft": 0}, {"xRight": 77, "yTop": 2556, "yBottom": 2582, "xLeft": 0}, {"xRight": 77, "yTop": 2607, "yBottom": 2624, "xLeft": 9}, {"xRight": 77, "yTop": 2641, "yBottom": 2667, "xLeft": 0}, {"xRight": 77, "yTop": 2727, "yBottom": 2752, "xLeft": 0}]}